docs/CHANGELOG.md
httprunner_ex/__init__.py
httprunner_ex/__main__.py
httprunner_ex/api.py
httprunner_ex/builtin/__init__.py
httprunner_ex/builtin/comparators.py
httprunner_ex/builtin/functions.py
httprunner_ex/cli.py
httprunner_ex/client.py
httprunner_ex/compat.py
httprunner_ex/context.py
httprunner_ex/exceptions.py
httprunner_ex/ext/__init__.py
httprunner_ex/ext/har2case/__init__.py
httprunner_ex/ext/locusts/__init__.py
httprunner_ex/ext/locusts/__main__.py
httprunner_ex/ext/locusts/cli.py
httprunner_ex/ext/locusts/locustfile_template.py
httprunner_ex/ext/locusts/README.md
httprunner_ex/ext/locusts/utils.py
httprunner_ex/ext/uploader/__init__.py
httprunner_ex/loader/__init__.py
httprunner_ex/loader/buildup.py
httprunner_ex/loader/check.py
httprunner_ex/loader/load.py
httprunner_ex/loader/locate.py
httprunner_ex/loader/schemas/api.schema.json
httprunner_ex/loader/schemas/common.schema.json
httprunner_ex/loader/schemas/testcase.schema.v1.json
httprunner_ex/loader/schemas/testcase.schema.v2.json
httprunner_ex/loader/schemas/testsuite.schema.v1.json
httprunner_ex/loader/schemas/testsuite.schema.v2.json
httprunner_ex/logger.py
httprunner_ex/parser.py
httprunner_ex/report/__init__.py
httprunner_ex/report/html/__init__.py
httprunner_ex/report/html/gen_report.py
httprunner_ex/report/html/result.py
httprunner_ex/report/html/template.html
httprunner_ex/report/report.py
httprunner_ex/report/stringify.py
httprunner_ex/report/summarize.py
httprunner_ex/response.py
httprunner_ex/runner.py
httprunner_ex/utils.py
httprunner_ex/validator.py
httprunner_ex-2.5.7.dist-info/entry_points.txt
httprunner_ex-2.5.7.dist-info/LICENSE
httprunner_ex-2.5.7.dist-info/WHEEL
httprunner_ex-2.5.7.dist-info/METADATA
httprunner_ex-2.5.7.dist-info/RECORD
