Metadata-Version: 2.1
Name: httprunner-ex
Version: 2.5.7
Summary: One-stop solution for HTTP(S) testing.
Home-page: https://github.com/httprunner/httprunner
License: Apache-2.0
Keywords: HTTP,api,test,requests,locustio
Author: debugtalk
Author-email: debugtalk@gmail.com
Requires-Python: >=2.7, !=3.0.*, !=3.1.*, !=3.2.*, !=3.3.*, !=3.4.*
Classifier: Development Status :: 5 - Production/Stable
Classifier: License :: OSI Approved :: Apache Software License
Classifier: Operating System :: MacOS
Classifier: Operating System :: Microsoft :: Windows
Classifier: Operating System :: POSIX :: Linux
Classifier: Programming Language :: Python :: 2
Classifier: Programming Language :: Python :: 2.7
Classifier: Programming Language :: Python :: 3
Classifier: Programming Language :: Python :: 3.5
Classifier: Programming Language :: Python :: 3.6
Classifier: Programming Language :: Python :: 3.7
Classifier: Programming Language :: Python :: 3.8
Classifier: Programming Language :: Python :: 3.9
Classifier: Topic :: Software Development :: Libraries :: Python Modules
Classifier: Topic :: Software Development :: Quality Assurance
Classifier: Topic :: Software Development :: Testing
Requires-Dist: colorama (>=0.4.1,<0.5.0)
Requires-Dist: colorlog (>=4.0.2,<5.0.0)
Requires-Dist: enum34 (>=1.1.6,<2.0.0); python_version >= "2.7" and python_version < "2.8"
Requires-Dist: filetype (>=1.0.5,<2.0.0)
Requires-Dist: future (>=0.18.1,<0.19.0); python_version >= "2.7" and python_version < "2.8"
Requires-Dist: har2case (>=0.3.1,<0.4.0)
Requires-Dist: jinja2 (>=2.10.3,<3.0.0)
Requires-Dist: jsonpath (>=0.82,<0.83)
Requires-Dist: jsonschema (>=3.2.0,<4.0.0)
Requires-Dist: pyyaml (>=5.1.2,<6.0.0)
Requires-Dist: requests (>=2.22.0,<3.0.0)
Requires-Dist: requests-toolbelt (>=0.9.1,<0.10.0)
Requires-Dist: sentry-sdk (>=0.13.5,<0.14.0)
Project-URL: Documentation, https://docs.httprunner.org
Project-URL: Repository, https://github.com/httprunner/httprunner
